{
  "schemaVersion": 1,
  "runtime": "quick",
  "slug": "blazon",
  "name": "БЛАЗОН: Доктрина",
  "shortName": "БЛАЗОН",
  "description": "Автономная битва равных армий с видимыми правилами герба, согласованными залпами и причинным разбором результата.",
  "version": "4.3.0",
  "releaseDate": "2026-07-18",
  "releaseDateTime": "2026-07-18T16:20:00+02:00",
  "changelog": [
    "Лучники выпускают согласованные залпы отделениями.",
    "Правила герба показываются непосредственно возле затронутого участка поля.",
    "Симуляция сохраняет компактные снимки и выбирает три ключевых момента.",
    "Послебоевой экран показывает фактические причины исхода.",
    "Мобильная вёрстка результата больше не обрезает показатели и действия."
  ],
  "status": "active",
  "preset": "game-2d",
  "accent": "#9a3438",
  "backgroundColor": "#171b17",
  "themeColor": "#171b17",
  "orientation": "portrait",
  "cacheName": "blazon-v4.3.0",
  "storageNamespace": "pocket-works:blazon",
  "tags": ["PWA","offline","game","strategy","autobattler","heraldry","medieval","simulation","roguelite","canvas","mobile"],
  "order": 76
}
